setlipy/__init__.py
setlipy/client.py
setlipy/string_encoding.py
setlipy-0.0.2.dist-info/LICENSE
setlipy-0.0.2.dist-info/METADATA
setlipy-0.0.2.dist-info/WHEEL
setlipy-0.0.2.dist-info/top_level.txt
setlipy-0.0.2.dist-info/RECORD
