Metadata-Version: 2.1
Name: setlipy
Version: 0.0.2
Summary: A simple Python wrapper for the setlist.fm API
Home-page: https://setlipy.readthedocs.io/
Author: Steffen Wiederspahn
License: UNKNOWN
Project-URL: Source, https://gitlab.com/cid88/setlistfmpy
Platform: UNKNOWN
Classifier: Programming Language :: Python :: 3
Classifier: License :: OSI Approved :: MIT License
Classifier: Operating System :: OS Independent
Requires-Python: >=3.7
License-File: LICENSE
Requires-Dist: requests (==2.28.1)
Requires-Dist: urllib3 (==1.26.12)
